application/__init__.py
application/abstract_registry.py
application/base_context_registry_locator.py
application/constants_interface.py
application/handler_map_factory.py
build/lib/application/__init__.py
build/lib/application/abstract_registry.py
build/lib/application/base_context_registry_locator.py
build/lib/application/constants_interface.py
build/lib/application/handler_map_factory.py
build/lib/build/lib/application/__init__.py
build/lib/build/lib/application/abstract_registry.py
build/lib/build/lib/application/base_context_registry_locator.py
build/lib/build/lib/application/constants_interface.py
build/lib/build/lib/application/handler_map_factory.py
build/lib/build/lib/enumeration/__init__.py
build/lib/build/lib/enumeration/enumerator/__init__.py
build/lib/build/lib/enumeration/enumerator/abstract_enumerator.py
build/lib/build/lib/enumeration/enumerator/basic_enumerator.py
build/lib/build/lib/enumeration/enums/__init__.py
build/lib/build/lib/enumeration/enums/abstract_enums.py
build/lib/build/lib/enumeration/enums/abstract_representable.py
build/lib/build/lib/enumeration/matcher/__init__.py
build/lib/build/lib/enumeration/matcher/abstract_matcher.py
build/lib/build/lib/enumeration/matcher/abstract_value_matcher.py
build/lib/build/lib/enumeration/visitor/__init__.py
build/lib/build/lib/enumeration/visitor/abstract_visitor.py
build/lib/build/lib/eventhandling/__init__.py
build/lib/build/lib/eventhandling/abstract_event_tracker.py
build/lib/build/lib/eventhandling/abstract_publisher.py
build/lib/build/lib/eventhandling/abstract_reaction.py
build/lib/build/lib/eventhandling/dummy_reaction.py
build/lib/build/lib/eventhandling/event.py
build/lib/build/lib/eventhandling/event_distributor.py
build/lib/build/lib/eventhandling/synchronized_event_tracker.py
build/lib/build/lib/eventhandling/value_change.py
build/lib/build/lib/eventhandling/eventmonitoring/__init__.py
build/lib/build/lib/eventhandling/eventmonitoring/abstract_base_event_monitor.py
thraxisgamespatterns-0.0.4.dist-info/METADATA
thraxisgamespatterns-0.0.4.dist-info/WHEEL
thraxisgamespatterns-0.0.4.dist-info/top_level.txt
thraxisgamespatterns-0.0.4.dist-info/RECORD
