Metadata-Version: 2.1
Name: thraxisgamespatterns
Version: 0.0.4
Summary: A series of python programming patterns to extend and ease implementation
Home-page: UNKNOWN
Author: Zack Simon
Author-email: zack.simon+thraxisgames@gmail.com
License: UNKNOWN
Platform: UNKNOWN
Classifier: Programming Language :: Python :: 3
Classifier: License :: OSI Approved :: MIT License
Classifier: Operating System :: OS Independent
